sjaicom_google_patents/__init__.py
sjaicom_google_patents/main.py
sjaicom_google_patents/models/__init__.py
sjaicom_google_patents/models/retrieval.py
sjaicom_google_patents/tools/__init__.py
sjaicom_google_patents/tools/interaction.py
sjaicom_google_patents/tools/patent_search.py
sjaicom_google_patents/utils.py
sjaicom_google_patents-0.1.11.dist-info/WHEEL
sjaicom_google_patents-0.1.11.dist-info/entry_points.txt
sjaicom_google_patents-0.1.11.dist-info/METADATA
sjaicom_google_patents-0.1.11.dist-info/RECORD
