Metadata-Version: 2.3
Name: sjaicom_google_patents
Version: 0.1.11
Summary: Add your description here
Author: dats
Author-email: dats <2292303916@qq.com>
Requires-Dist: fastmcp>=2.14.1
Requires-Dist: pydantic>=2.12.5
Requires-Dist: python-dotenv>=1.0.0
Requires-Dist: requests>=2.31.0
Requires-Python: >=3.10
